BBData/__init__.py
BBData/config.py
BBData/lib.py
BBData/reader_utils.py
BBData/saver_utils.py
BBData/tools.py
BBData/utils.py
LGNB-9.7.12.dist-info/LICENSE
LGNB-9.7.12.dist-info/METADATA
LGNB-9.7.12.dist-info/WHEEL
LGNB-9.7.12.dist-info/top_level.txt
LGNB-9.7.12.dist-info/RECORD
