Metadata-Version: 2.1
Name: LGNB
Version: 9.7.12
Summary: data api
Home-page: https://oa.csc.com.cn
Author: wangcc
Author-email: 705190651@qq.com
License: UNKNOWN
Platform: UNKNOWN
License-File: LICENSE
